traicionar/__init__.py
traicionar-0.0.3.dist-info/LICENSE
traicionar-0.0.3.dist-info/METADATA
traicionar-0.0.3.dist-info/WHEEL
traicionar-0.0.3.dist-info/top_level.txt
traicionar-0.0.3.dist-info/RECORD
