Metadata-Version: 2.1
Name: traicionar
Version: 0.0.3
Summary: library for electronic betrayal
Home-page: https://github.com/montoyamoraga/traicionar.py
Author: montoyamoraga
Author-email: montoyamoraga@gmail.com
License: MIT
Classifier: Programming Language :: Python :: 3
Classifier: Development Status :: 3 - Alpha
License-File: LICENSE
